pb/__init__.py
pb/error_event.py
pb/error_handler.py
pb/publish_event.py
pb/pubsub_exceptions.py
shipmnts_pubsub-0.0.38.dist-info/LICENSE
shipmnts_pubsub-0.0.38.dist-info/METADATA
shipmnts_pubsub-0.0.38.dist-info/WHEEL
shipmnts_pubsub-0.0.38.dist-info/top_level.txt
shipmnts_pubsub-0.0.38.dist-info/RECORD
