Metadata-Version: 2.1
Name: shipmnts-pubsub
Version: 0.0.38
Summary: Pubsub handler
Home-page: https://github.com/vimox-shah/shipmnts_pubsub
Author: Vimox Shah
Author-email: vimox@shipmnts.com
License: UNKNOWN
Platform: UNKNOWN
Classifier: Programming Language :: Python :: 3
Classifier: License :: OSI Approved :: MIT License
Classifier: Operating System :: OS Independent
License-File: LICENSE
Requires-Dist: google-cloud-pubsub (==2.6.0)
